com_digitalruiz_shopify_tools/__init__.py
com_digitalruiz_shopify_tools/shopify_tools.py
com_digitalruiz_shopify_tools-0.0.16.dist-info/LICENSE
com_digitalruiz_shopify_tools-0.0.16.dist-info/METADATA
com_digitalruiz_shopify_tools-0.0.16.dist-info/WHEEL
com_digitalruiz_shopify_tools-0.0.16.dist-info/top_level.txt
com_digitalruiz_shopify_tools-0.0.16.dist-info/RECORD
