Metadata-Version: 2.1
Name: com_digitalruiz_shopify_tools
Version: 0.0.16
Summary: Collections of custom shopify functions
Author-email: Reyes Ruiz <reyes@digitalruiz.com>
Project-URL: Homepage, https://github.com/reyesruiz/shopify_tools
Project-URL: Bug Tracker, https://github.com/reyesruiz/shopify_tools/issues
Classifier: Programming Language :: Python :: 3
Classifier: License :: OSI Approved :: MIT License
Classifier: Operating System :: OS Independent
Requires-Python: >=3.7
License-File: LICENSE
Requires-Dist: com-digitalruiz-my-logger
Requires-Dist: com-digitalruiz-shopify-apis
